checkov/__init__.py
checkov/logging_init.py
checkov/main.py
checkov/runner_filter.py
checkov/version.py
checkov/arm/__init__.py
checkov/arm/base_registry.py
checkov/arm/base_resource_check.py
checkov/arm/base_resource_value_check.py
checkov/arm/context_parser.py
checkov/arm/registry.py
checkov/arm/runner.py
checkov/arm/checks/AKSApiServerAuthorizedIpRanges.py
checkov/arm/checks/AKSDashboardDisabled.py
checkov/arm/checks/AKSLoggingEnabled.py
checkov/arm/checks/AKSNetworkPolicy.py
checkov/arm/checks/AKSRbacEnabled.py
checkov/arm/checks/AppServiceAuthentication.py
checkov/arm/checks/AppServiceClientCertificate.py
checkov/arm/checks/AppServiceHTTPSOnly.py
checkov/arm/checks/AppServiceHttps20Enabled.py
checkov/arm/checks/AppServiceIdentity.py
checkov/arm/checks/AppServiceMinTLSVersion.py
checkov/arm/checks/AzureInstancePassword.py
checkov/arm/checks/AzureManagedDiscEncryption.py
checkov/arm/checks/CustomRoleDefinitionSubscriptionOwner.py
checkov/arm/checks/KeyvaultRecoveryEnabled.py
checkov/arm/checks/MonitorLogProfileCategories.py
checkov/arm/checks/MonitorLogProfileRetentionDays.py
checkov/arm/checks/MySQLServerSSLEnforcementEnabled.py
checkov/arm/checks/NSGRulePortAccessRestricted.py
checkov/arm/checks/NSGRuleRDPAccessRestricted.py
checkov/arm/checks/NSGRuleSSHAccessRestricted.py
checkov/arm/checks/NetworkWatcherFlowLogPeriod.py
checkov/arm/checks/PostgreSQLServerConnectionThrottlingEnabled.py
checkov/arm/checks/PostgreSQLServerLogCheckpointsEnabled.py
checkov/arm/checks/PostgreSQLServerLogConnectionsEnabled.py
checkov/arm/checks/PostgreSQLServerSSLEnforcementEnabled.py
checkov/arm/checks/SQLServerAuditingEnabled.py
checkov/arm/checks/SQLServerAuditingRetention90Days.py
checkov/arm/checks/SQLServerEmailAlertsEnabled.py
checkov/arm/checks/SQLServerEmailAlertsToAdminsEnabled.py
checkov/arm/checks/SQLServerNoPublicAccess.py
checkov/arm/checks/SQLServerThreatDetectionTypes.py
checkov/arm/checks/SecretExpirationDate.py
checkov/arm/checks/SecurityCenterContactEmailAlert.py
checkov2-1.0.970.dist-info/LICENSE
checkov2-1.0.970.dist-info/METADATA
checkov2-1.0.970.dist-info/WHEEL
checkov2-1.0.970.dist-info/top_level.txt
checkov2-1.0.970.dist-info/RECORD
