Metadata-Version: 2.1
Name: checkov2
Version: 1.0.970
Summary: Infrastructure as code static analysis
Home-page: https://github.com/nimrodkor/checkov
Author: bridgecrew
Author-email: meet@bridgecrew.io
License: Apache License 2.0
Platform: UNKNOWN
Classifier: Environment :: Console
Classifier: Intended Audience :: Developers
Classifier: Intended Audience :: System Administrators
Classifier: Programming Language :: Python :: 3.7
Classifier: Topic :: Security
Classifier: Topic :: Software Development :: Build Tools
Requires-Python: >=3.7
Requires-Dist: bc-python-hcl2 (>=0.3.18)
Requires-Dist: cloudsplaining (>=0.3.2)
Requires-Dist: deep-merge
Requires-Dist: tabulate
Requires-Dist: colorama
Requires-Dist: termcolor
Requires-Dist: junit-xml
Requires-Dist: dpath (<2,>=1.5.0)
Requires-Dist: pyyaml (>=5.4.1)
Requires-Dist: boto3
Requires-Dist: GitPython
Requires-Dist: six (==1.15.0)
Requires-Dist: jmespath
Requires-Dist: tqdm
Requires-Dist: update-checker
Requires-Dist: semantic-version
Requires-Dist: packaging
Requires-Dist: networkx
Requires-Dist: dockerfile-parse
Provides-Extra: dev
Requires-Dist: pytest (==5.3.1) ; extra == 'dev'
Requires-Dist: coverage ; extra == 'dev'
Requires-Dist: coverage-badge ; extra == 'dev'
Requires-Dist: pipenv-setup ; extra == 'dev'
Requires-Dist: GitPython (==3.1.7) ; extra == 'dev'
Requires-Dist: bandit ; extra == 'dev'
